CMakeLists.txt
LICENSE
MANIFEST.in
README.md
pyproject.toml
requirements.txt
setup.py
ext/pybind/CMakeLists.txt
ext/pybind/include/pybind11/attr.h
ext/pybind/include/pybind11/buffer_info.h
ext/pybind/include/pybind11/cast.h
ext/pybind/include/pybind11/chrono.h
ext/pybind/include/pybind11/common.h
ext/pybind/include/pybind11/complex.h
ext/pybind/include/pybind11/eigen.h
ext/pybind/include/pybind11/embed.h
ext/pybind/include/pybind11/eval.h
ext/pybind/include/pybind11/functional.h
ext/pybind/include/pybind11/gil.h
ext/pybind/include/pybind11/gil_safe_call_once.h
ext/pybind/include/pybind11/iostream.h
ext/pybind/include/pybind11/numpy.h
ext/pybind/include/pybind11/operators.h
ext/pybind/include/pybind11/options.h
ext/pybind/include/pybind11/pybind11.h
ext/pybind/include/pybind11/pytypes.h
ext/pybind/include/pybind11/stl.h
ext/pybind/include/pybind11/stl_bind.h
ext/pybind/include/pybind11/type_caster_pyobject_ptr.h
ext/pybind/include/pybind11/typing.h
ext/pybind/include/pybind11/detail/class.h
ext/pybind/include/pybind11/detail/common.h
ext/pybind/include/pybind11/detail/descr.h
ext/pybind/include/pybind11/detail/init.h
ext/pybind/include/pybind11/detail/internals.h
ext/pybind/include/pybind11/detail/type_caster_base.h
ext/pybind/include/pybind11/detail/typeid.h
ext/pybind/include/pybind11/eigen/common.h
ext/pybind/include/pybind11/eigen/matrix.h
ext/pybind/include/pybind11/eigen/tensor.h
ext/pybind/include/pybind11/stl/filesystem.h
ext/pybind/tests/CMakeLists.txt
ext/pybind/tests/test_cmake_build/CMakeLists.txt
ext/pybind/tests/test_cmake_build/installed_embed/CMakeLists.txt
ext/pybind/tests/test_cmake_build/installed_function/CMakeLists.txt
ext/pybind/tests/test_cmake_build/installed_target/CMakeLists.txt
ext/pybind/tests/test_cmake_build/subdirectory_embed/CMakeLists.txt
ext/pybind/tests/test_cmake_build/subdirectory_function/CMakeLists.txt
ext/pybind/tests/test_cmake_build/subdirectory_target/CMakeLists.txt
ext/pybind/tests/test_embed/CMakeLists.txt
pqkmeans.egg-info/PKG-INFO
pqkmeans.egg-info/SOURCES.txt
pqkmeans.egg-info/dependency_links.txt
pqkmeans.egg-info/not-zip-safe
pqkmeans.egg-info/requires.txt
pqkmeans.egg-info/top_level.txt
