Metadata-Version: 2.1
Name: pqkmeans
Version: 1.0.6
Summary: Fast and memory-efficient clustering
Home-page: http://yusukematsui.me/project/pqkmeans/pqkmeans.html
Author: Keisuke Ogaki, Yusuke Matsui
Author-email: keisuke_ogaki@dwango.co.jp, matsui528@gmail.com
License: MIT License
Provides-Extra: texmex
License-File: LICENSE
